check_keepass_passwords/__init__.py
check_keepass_passwords/checker.py
check_keepass_passwords/cli.py
check_keepass_passwords-0.1.dist-info/METADATA
check_keepass_passwords-0.1.dist-info/WHEEL
check_keepass_passwords-0.1.dist-info/entry_points.txt
check_keepass_passwords-0.1.dist-info/RECORD
