Metadata-Version: 2.1
Name: check-keepass-passwords
Version: 0.1
Summary: A command-line tool that scans Keepass 2.x databases for weak or compromised passwords
License: MIT
Author: Tomas Bayer
Author-email: mail@tomas.berlin
Requires-Python: >=3.11,<4.0
Classifier: License :: OSI Approved :: MIT License
Classifier: Programming Language :: Python :: 3
Classifier: Programming Language :: Python :: 3.11
Classifier: Programming Language :: Python :: 3.12
Requires-Dist: pwnedpasswords (>=2.0.0,<3.0.0)
Requires-Dist: pykeepass (>=4.0.6,<5.0.0)
Requires-Dist: rich (>=13.7.0,<14.0.0)
Requires-Dist: typer[all] (>=0.9.0,<0.10.0)
